README.rst
setup.py
fuzzy.ai.egg-info/PKG-INFO
fuzzy.ai.egg-info/SOURCES.txt
fuzzy.ai.egg-info/dependency_links.txt
fuzzy.ai.egg-info/requires.txt
fuzzy.ai.egg-info/top_level.txt
fuzzyai/__init__.py
fuzzyai/client.py
fuzzyai/version.py
fuzzyai/test/__init__.py
fuzzyai/test/test_client.py