Metadata-Version: 1.0
Name: fuzzy.ai
Version: 0.3.1
Summary: fuzzy.ai API
Home-page: https://github.com/fuzzy-ai/fuzzy.ai-python
Author: Evan Prodromou
Author-email: evan@fuzzy.ai
License: Apache 2.0
Platform: UNKNOWN
